[
  {
    "data": [
      {
        "humidity": 53.8,
        "rainfall": 0.0,
        "snow_cover": 0.0,
        "snowfall_3hr": 0.0,
        "temperature": 23.8,
        "time": "2025-04-21T12:25:00+09:00",
        "wind_speed": 1.1
      }
    ],
    "location": {
      "latitude": 37.336926,
      "longitude": 127.293508
    },
    "name": "스키하우스",
    "resort": "곤지암리조트",
    "timestamp": "2025-04-21T13:27:10.600273+09:00"
  },
  {
    "data": [
      {
        "humidity": 52.9,
        "rainfall": 0.0,
        "snow_cover": 0.0,
        "snowfall_3hr": 0.0,
        "temperature": 24.4,
        "time": "2025-04-21T12:25:00+09:00",
        "wind_speed": 1.3
      }
    ],
    "location": {
      "latitude": 37.217222,
      "longitude": 127.344901
    },
    "name": "스키하우스",
    "resort": "지산 포레스트 리조트",
    "timestamp": "2025-04-21T13:27:11.106433+09:00"
  },
  {
    "data": [
      {
        "humidity": 54.0,
        "rainfall": 0.0,
        "snow_cover": 0.0,
        "snowfall_3hr": 0.0,
        "temperature": 24.2,
        "time": "2025-04-21T12:25:00+09:00",
        "wind_speed": 1.3
      }
    ],
    "location": {
      "latitude": 37.211455,
      "longitude": 127.339681
    },
    "name": "블루 정상",
    "resort": "지산 포레스트 리조트",
    "timestamp": "2025-04-21T13:27:11.308853+09:00"
  },
  {
    "data": [
      {
        "humidity": 45.9,
        "rainfall": 0.0,
        "snow_cover": 0.0,
        "snowfall_3hr": 0.0,
        "temperature": 24.4,
        "time": "2025-04-21T12:25:00+09:00",
        "wind_speed": 1.0
      }
    ],
    "location": {
      "latitude": 37.820268,
      "longitude": 127.590066
    },
    "name": "스키하우스",
    "resort": "엘리시안 강촌",
    "timestamp": "2025-04-21T13:27:11.511367+09:00"
  },
  {
    "data": [
      {
        "humidity": 45.4,
        "rainfall": 0.0,
        "snow_cover": 0.0,
        "snowfall_3hr": 0.0,
        "temperature": 24.8,
        "time": "2025-04-21T12:25:00+09:00",
        "wind_speed": 1.0
      }
    ],
    "location": {
      "latitude": 37.815248,
      "longitude": 127.58271
    },
    "name": "정상",
    "resort": "엘리시안 강촌",
    "timestamp": "2025-04-21T13:27:11.612514+09:00"
  },
  {
    "data": [
      {
        "humidity": 51.4,
        "rainfall": 0.0,
        "snow_cover": 0.0,
        "snowfall_3hr": 0.0,
        "temperature": 22.8,
        "time": "2025-04-21T12:25:00+09:00",
        "wind_speed": 1.4
      }
    ],
    "location": {
      "latitude": 37.64481,
      "longitude": 127.68212
    },
    "name": "스키하우스",
    "resort": "비발디파크",
    "timestamp": "2025-04-21T13:27:11.916126+09:00"
  },
  {
    "data": [
      {
        "humidity": 47.5,
        "rainfall": 0.0,
        "snow_cover": 0.0,
        "snowfall_3hr": 0.0,
        "temperature": 23.3,
        "time": "2025-04-21T12:25:00+09:00",
        "wind_speed": 1.5
      }
    ],
    "location": {
      "latitude": 37.63745,
      "longitude": 127.690009
    },
    "name": "정상",
    "resort": "비발디파크",
    "timestamp": "2025-04-21T13:27:12.017365+09:00"
  },
  {
    "data": [
      {
        "humidity": 49.8,
        "rainfall": 0.0,
        "snow_cover": 0.0,
        "snowfall_3hr": 0.0,
        "temperature": 24.2,
        "time": "2025-04-21T12:25:00+09:00",
        "wind_speed": 2.1
      }
    ],
    "location": {
      "latitude": 37.407486,
      "longitude": 127.807955
    },
    "name": "스키하우스",
    "resort": "오크밸리",
    "timestamp": "2025-04-21T13:27:12.320950+09:00"
  },
  {
    "data": [
      {
        "humidity": 48.3,
        "rainfall": 0.0,
        "snow_cover": 0.0,
        "snowfall_3hr": 0.0,
        "temperature": 23.5,
        "time": "2025-04-21T12:25:00+09:00",
        "wind_speed": 2.1
      }
    ],
    "location": {
      "latitude": 37.402345,
      "longitude": 127.819064
    },
    "name": "정상",
    "resort": "오크밸리",
    "timestamp": "2025-04-21T13:27:12.422067+09:00"
  },
  {
    "data": [
      {
        "humidity": 40.9,
        "rainfall": 0.0,
        "snow_cover": 0.0,
        "snowfall_3hr": 0.0,
        "temperature": 22.4,
        "time": "2025-04-21T12:25:00+09:00",
        "wind_speed": 1.2
      }
    ],
    "location": {
      "latitude": 37.490504,
      "longitude": 128.249569
    },
    "name": "스키하우스",
    "resort": "웰리힐리파크",
    "timestamp": "2025-04-21T13:27:12.725755+09:00"
  },
  {
    "data": [
      {
        "humidity": 42.3,
        "rainfall": 0.0,
        "snow_cover": 0.0,
        "snowfall_3hr": 0.0,
        "temperature": 22.7,
        "time": "2025-04-21T12:25:00+09:00",
        "wind_speed": 1.2
      }
    ],
    "location": {
      "latitude": 37.480179,
      "longitude": 128.243631
    },
    "name": "정상",
    "resort": "웰리힐리파크",
    "timestamp": "2025-04-21T13:27:12.826950+09:00"
  },
  {
    "data": [
      {
        "humidity": 38.0,
        "rainfall": 0.0,
        "snow_cover": 0.0,
        "snowfall_3hr": 0.0,
        "temperature": 21.4,
        "time": "2025-04-21T12:25:00+09:00",
        "wind_speed": 0.5
      }
    ],
    "location": {
      "latitude": 37.656947,
      "longitude": 128.672346
    },
    "name": "스키하우스",
    "resort": "알펜시아 리조트",
    "timestamp": "2025-04-21T13:27:13.535116+09:00"
  },
  {
    "data": [
      {
        "humidity": 37.9,
        "rainfall": 0.0,
        "snow_cover": 0.0,
        "snowfall_3hr": 0.0,
        "temperature": 21.4,
        "time": "2025-04-21T12:25:00+09:00",
        "wind_speed": 0.4
      }
    ],
    "location": {
      "latitude": 37.650037,
      "longitude": 128.673341
    },
    "name": "정상",
    "resort": "알펜시아 리조트",
    "timestamp": "2025-04-21T13:27:13.636248+09:00"
  },
  {
    "data": [
      {
        "humidity": 38.9,
        "rainfall": 0.0,
        "snow_cover": 0.0,
        "snowfall_3hr": 0.0,
        "temperature": 21.0,
        "time": "2025-04-21T12:25:00+09:00",
        "wind_speed": 0.4
      }
    ],
    "location": {
      "latitude": 37.644475,
      "longitude": 128.679931
    },
    "name": "스키하우스",
    "resort": "모나 용평",
    "timestamp": "2025-04-21T13:27:13.839164+09:00"
  },
  {
    "data": [
      {
        "humidity": 41.3,
        "rainfall": 0.0,
        "snow_cover": 0.0,
        "snowfall_3hr": 0.0,
        "temperature": 18.5,
        "time": "2025-04-21T12:25:00+09:00",
        "wind_speed": 0.2
      }
    ],
    "location": {
      "latitude": 37.622619,
      "longitude": 128.663407
    },
    "name": "레인보우 베이스",
    "resort": "모나 용평",
    "timestamp": "2025-04-21T13:27:13.940302+09:00"
  },
  {
    "data": [
      {
        "humidity": 53.3,
        "rainfall": 0.0,
        "snow_cover": 0.0,
        "snowfall_3hr": 0.0,
        "temperature": 15.6,
        "time": "2025-04-21T12:25:00+09:00",
        "wind_speed": 0.2
      }
    ],
    "location": {
      "latitude": 37.611407,
      "longitude": 128.671577
    },
    "name": "레인보우 정상",
    "resort": "모나 용평",
    "timestamp": "2025-04-21T13:27:14.040731+09:00"
  },
  {
    "data": [
      {
        "humidity": 39.3,
        "rainfall": 0.0,
        "snow_cover": 0.0,
        "snowfall_3hr": 0.0,
        "temperature": 20.3,
        "time": "2025-04-21T12:25:00+09:00",
        "wind_speed": 0.3
      }
    ],
    "location": {
      "latitude": 37.633116,
      "longitude": 128.675128
    },
    "name": "실버 정상",
    "resort": "모나 용평",
    "timestamp": "2025-04-21T13:27:14.141990+09:00"
  },
  {
    "data": [
      {
        "humidity": 39.4,
        "rainfall": 0.0,
        "snow_cover": 0.0,
        "snowfall_3hr": 0.0,
        "temperature": 21.1,
        "time": "2025-04-21T12:25:00+09:00",
        "wind_speed": 0.3
      }
    ],
    "location": {
      "latitude": 37.636119,
      "longitude": 128.683102
    },
    "name": "레드 정상",
    "resort": "모나 용평",
    "timestamp": "2025-04-21T13:27:14.344256+09:00"
  },
  {
    "data": [
      {
        "humidity": 36.8,
        "rainfall": 0.0,
        "snow_cover": 0.0,
        "snowfall_3hr": 0.0,
        "temperature": 21.7,
        "time": "2025-04-21T12:25:00+09:00",
        "wind_speed": 0.4
      }
    ],
    "location": {
      "latitude": 37.638654,
      "longitude": 128.686773
    },
    "name": "골드 베이스",
    "resort": "모나 용평",
    "timestamp": "2025-04-21T13:27:14.777098+09:00"
  },
  {
    "data": [
      {
        "humidity": 42.9,
        "rainfall": 0.0,
        "snow_cover": 0.0,
        "snowfall_3hr": 0.0,
        "temperature": 18.3,
        "time": "2025-04-21T12:25:00+09:00",
        "wind_speed": 0.3
      }
    ],
    "location": {
      "latitude": 37.623744,
      "longitude": 128.686841
    },
    "name": "골드 정상",
    "resort": "모나 용평",
    "timestamp": "2025-04-21T13:27:14.874706+09:00"
  },
  {
    "data": [
      {
        "humidity": 48.8,
        "rainfall": 0.0,
        "snow_cover": 0.0,
        "snowfall_3hr": 0.0,
        "temperature": 18.9,
        "time": "2025-04-21T12:25:00+09:00",
        "wind_speed": 3.3
      }
    ],
    "location": {
      "latitude": 37.177413,
      "longitude": 128.947762
    },
    "name": "스키하우스",
    "resort": "오투리조트",
    "timestamp": "2025-04-21T13:27:15.346410+09:00"
  },
  {
    "data": [
      {
        "humidity": 48.4,
        "rainfall": 0.0,
        "snow_cover": 0.0,
        "snowfall_3hr": 0.0,
        "temperature": 18.9,
        "time": "2025-04-21T12:25:00+09:00",
        "wind_speed": 3.3
      }
    ],
    "location": {
      "latitude": 37.171071,
      "longitude": 128.947326
    },
    "name": "글로리 정상 (콘도)",
    "resort": "오투리조트",
    "timestamp": "2025-04-21T13:27:15.446557+09:00"
  },
  {
    "data": [
      {
        "humidity": 47.4,
        "rainfall": 0.0,
        "snow_cover": 0.0,
        "snowfall_3hr": 0.0,
        "temperature": 16.5,
        "time": "2025-04-21T12:25:00+09:00",
        "wind_speed": 3.5
      }
    ],
    "location": {
      "latitude": 37.17106,
      "longitude": 128.938784
    },
    "name": "버금마루",
    "resort": "오투리조트",
    "timestamp": "2025-04-21T13:27:15.703587+09:00"
  },
  {
    "data": [
      {
        "humidity": 57.6,
        "rainfall": 0.0,
        "snow_cover": 0.0,
        "snowfall_3hr": 0.0,
        "temperature": 14.9,
        "time": "2025-04-21T12:25:00+09:00",
        "wind_speed": 3.7
      }
    ],
    "location": {
      "latitude": 37.167622,
      "longitude": 128.926934
    },
    "name": "으뜸마루",
    "resort": "오투리조트",
    "timestamp": "2025-04-21T13:27:15.884312+09:00"
  },
  {
    "data": [
      {
        "humidity": 57.4,
        "rainfall": 0.0,
        "snow_cover": 0.0,
        "snowfall_3hr": 0.0,
        "temperature": 18.4,
        "time": "2025-04-21T12:25:00+09:00",
        "wind_speed": 0.9
      }
    ],
    "location": {
      "latitude": 35.42875,
      "longitude": 128.984464
    },
    "name": "스키하우스",
    "resort": "에덴밸리리조트",
    "timestamp": "2025-04-21T13:27:17.363628+09:00"
  },
  {
    "data": [
      {
        "humidity": 57.5,
        "rainfall": 0.0,
        "snow_cover": 0.0,
        "snowfall_3hr": 0.0,
        "temperature": 18.3,
        "time": "2025-04-21T12:25:00+09:00",
        "wind_speed": 0.9
      }
    ],
    "location": {
      "latitude": 35.419484,
      "longitude": 128.983221
    },
    "name": "정상",
    "resort": "에덴밸리리조트",
    "timestamp": "2025-04-21T13:27:17.728017+09:00"
  },
  {
    "data": [
      {
        "humidity": 52.5,
        "rainfall": 0.0,
        "snow_cover": 0.0,
        "snowfall_3hr": 0.0,
        "temperature": 22.1,
        "time": "2025-04-21T12:25:00+09:00",
        "wind_speed": 1.1
      }
    ],
    "location": {
      "latitude": 37.328921,
      "longitude": 127.281187
    },
    "name": "정상",
    "resort": "곤지암리조트",
    "timestamp": "2025-04-21T13:27:10.701509+09:00"
  },
  {
    "data": [
      {
        "humidity": 53.9,
        "rainfall": 0.0,
        "snow_cover": 0.0,
        "snowfall_3hr": 0.0,
        "temperature": 24.2,
        "time": "2025-04-21T12:25:00+09:00",
        "wind_speed": 1.4
      }
    ],
    "location": {
      "latitude": 37.209838,
      "longitude": 127.343431
    },
    "name": "뉴오렌지 정상",
    "resort": "지산 포레스트 리조트",
    "timestamp": "2025-04-21T13:27:11.207707+09:00"
  },
  {
    "data": [
      {
        "humidity": 54.0,
        "rainfall": 0.0,
        "snow_cover": 0.0,
        "snowfall_3hr": 0.0,
        "temperature": 24.2,
        "time": "2025-04-21T12:25:00+09:00",
        "wind_speed": 1.3
      }
    ],
    "location": {
      "latitude": 37.213011,
      "longitude": 127.339173
    },
    "name": "실버 정상",
    "resort": "지산 포레스트 리조트",
    "timestamp": "2025-04-21T13:27:11.410087+09:00"
  },
  {
    "data": [
      {
        "humidity": 45.4,
        "rainfall": 0.0,
        "snow_cover": 0.0,
        "snowfall_3hr": 0.0,
        "temperature": 24.8,
        "time": "2025-04-21T12:25:00+09:00",
        "wind_speed": 1.0
      }
    ],
    "location": {
      "latitude": 37.81424,
      "longitude": 127.587458
    },
    "name": "래빗 상단",
    "resort": "엘리시안 강촌",
    "timestamp": "2025-04-21T13:27:11.713520+09:00"
  },
  {
    "data": [
      {
        "humidity": 45.4,
        "rainfall": 0.0,
        "snow_cover": 0.0,
        "snowfall_3hr": 0.0,
        "temperature": 24.8,
        "time": "2025-04-21T12:25:00+09:00",
        "wind_speed": 1.0
      }
    ],
    "location": {
      "latitude": 37.818119,
      "longitude": 127.584561
    },
    "name": "레퍼드 상단",
    "resort": "엘리시안 강촌",
    "timestamp": "2025-04-21T13:27:11.814822+09:00"
  },
  {
    "data": [
      {
        "humidity": 48.2,
        "rainfall": 0.0,
        "snow_cover": 0.0,
        "snowfall_3hr": 0.0,
        "temperature": 23.1,
        "time": "2025-04-21T12:25:00+09:00",
        "wind_speed": 1.5
      }
    ],
    "location": {
      "latitude": 37.64246,
      "longitude": 127.692647
    },
    "name": "재즈 상단",
    "resort": "비발디파크",
    "timestamp": "2025-04-21T13:27:12.118581+09:00"
  },
  {
    "data": [
      {
        "humidity": 47.9,
        "rainfall": 0.0,
        "snow_cover": 0.0,
        "snowfall_3hr": 0.0,
        "temperature": 23.2,
        "time": "2025-04-21T12:25:00+09:00",
        "wind_speed": 1.5
      }
    ],
    "location": {
      "latitude": 37.639005,
      "longitude": 127.684443
    },
    "name": "힙합 상단",
    "resort": "비발디파크",
    "timestamp": "2025-04-21T13:27:12.219769+09:00"
  },
  {
    "data": [
      {
        "humidity": 50.6,
        "rainfall": 0.0,
        "snow_cover": 0.0,
        "snowfall_3hr": 0.0,
        "temperature": 23.9,
        "time": "2025-04-21T12:25:00+09:00",
        "wind_speed": 2.1
      }
    ],
    "location": {
      "latitude": 37.402541,
      "longitude": 127.812239
    },
    "name": "버드 정상",
    "resort": "오크밸리",
    "timestamp": "2025-04-21T13:27:12.523207+09:00"
  },
  {
    "data": [
      {
        "humidity": 50.5,
        "rainfall": 0.0,
        "snow_cover": 0.0,
        "snowfall_3hr": 0.0,
        "temperature": 23.8,
        "time": "2025-04-21T12:25:00+09:00",
        "wind_speed": 2.1
      }
    ],
    "location": {
      "latitude": 37.408135,
      "longitude": 127.814674
    },
    "name": "플라워 휴게소",
    "resort": "오크밸리",
    "timestamp": "2025-04-21T13:27:12.624575+09:00"
  },
  {
    "data": [
      {
        "humidity": 42.5,
        "rainfall": 0.0,
        "snow_cover": 0.0,
        "snowfall_3hr": 0.0,
        "temperature": 22.7,
        "time": "2025-04-21T12:25:00+09:00",
        "wind_speed": 1.1
      }
    ],
    "location": {
      "latitude": 37.481028,
      "longitude": 128.248959
    },
    "name": "뉴브라보 정상",
    "resort": "웰리힐리파크",
    "timestamp": "2025-04-21T13:27:12.927973+09:00"
  },
  {
    "data": [
      {
        "humidity": 37.8,
        "rainfall": 0.0,
        "snow_cover": 0.0,
        "snowfall_3hr": 0.0,
        "temperature": 21.5,
        "time": "2025-04-21T12:25:00+09:00",
        "wind_speed": 0.4
      }
    ],
    "location": {
      "latitude": 37.651708,
      "longitude": 128.668917
    },
    "name": "알파 상단",
    "resort": "알펜시아 리조트",
    "timestamp": "2025-04-21T13:27:13.737584+09:00"
  },
  {
    "data": [
      {
        "humidity": 38.2,
        "rainfall": 0.0,
        "snow_cover": 0.0,
        "snowfall_3hr": 0.0,
        "temperature": 21.2,
        "time": "2025-04-21T12:25:00+09:00",
        "wind_speed": 0.3
      }
    ],
    "location": {
      "latitude": 37.636661,
      "longitude": 128.673182
    },
    "name": "메가그린 상단",
    "resort": "모나 용평",
    "timestamp": "2025-04-21T13:27:14.243109+09:00"
  },
  {
    "data": [
      {
        "humidity": 36.9,
        "rainfall": 0.0,
        "snow_cover": 0.0,
        "snowfall_3hr": 0.0,
        "temperature": 19.7,
        "time": "2025-04-21T12:25:00+09:00",
        "wind_speed": 0.3
      }
    ],
    "location": {
      "latitude": 37.631921,
      "longitude": 128.685477
    },
    "name": "뉴골드 상단",
    "resort": "모나 용평",
    "timestamp": "2025-04-21T13:27:14.523568+09:00"
  },
  {
    "data": [
      {
        "humidity": 48.0,
        "rainfall": 0.0,
        "snow_cover": 0.0,
        "snowfall_3hr": 0.0,
        "temperature": 16.5,
        "time": "2025-04-21T12:25:00+09:00",
        "wind_speed": 3.5
      }
    ],
    "location": {
      "latitude": 37.1763619,
      "longitude": 128.930526
    },
    "name": "드림 상단",
    "resort": "오투리조트",
    "timestamp": "2025-04-21T13:27:15.893204+09:00"
  },
  {
    "data": [
      {
        "humidity": 56.3,
        "rainfall": 0.0,
        "snow_cover": 0.0,
        "snowfall_3hr": 0.0,
        "temperature": 18.7,
        "time": "2025-04-21T12:25:00+09:00",
        "wind_speed": 0.9
      }
    ],
    "location": {
      "latitude": 35.419484,
      "longitude": 128.98871
    },
    "name": "에덴리프트 상단",
    "resort": "에덴밸리리조트",
    "timestamp": "2025-04-21T13:27:17.729337+09:00"
  },
  {
    "data": [
      {
        "humidity": 38.6,
        "rainfall": 0.0,
        "snow_cover": 0.0,
        "snowfall_3hr": 0.0,
        "temperature": 23.2,
        "time": "2025-04-21T12:25:00+09:00",
        "wind_speed": 1.0
      }
    ],
    "location": {
      "latitude": 37.474014,
      "longitude": 128.60972
    },
    "name": "스키하우스",
    "resort": "정선 알파인 경기장",
    "timestamp": "2025-04-21T13:27:17.742840+09:00"
  },
  {
    "data": [
      {
        "humidity": 43.3,
        "rainfall": 0.0,
        "snow_cover": 0.0,
        "snowfall_3hr": 0.0,
        "temperature": 18.7,
        "time": "2025-04-21T12:25:00+09:00",
        "wind_speed": 1.0
      }
    ],
    "location": {
      "latitude": 37.444482,
      "longitude": 128.597952
    },
    "name": "정상",
    "resort": "정선 알파인 경기장",
    "timestamp": "2025-04-21T13:27:17.744790+09:00"
  },
  {
    "data": [
      {
        "humidity": 50.8,
        "rainfall": 0.0,
        "snow_cover": 0.0,
        "snowfall_3hr": 0.0,
        "temperature": 22.0,
        "time": "2025-04-21T12:25:00+09:00",
        "wind_speed": 1.1
      }
    ],
    "location": {
      "latitude": 37.329382,
      "longitude": 127.287927
    },
    "name": "스톰 정상",
    "resort": "곤지암리조트",
    "timestamp": "2025-04-21T13:27:10.802699+09:00"
  },
  {
    "data": [
      {
        "humidity": 37.7,
        "rainfall": 0.0,
        "snow_cover": 0.0,
        "snowfall_3hr": 0.0,
        "temperature": 22.2,
        "time": "2025-04-21T12:25:00+09:00",
        "wind_speed": 1.1
      }
    ],
    "location": {
      "latitude": 37.583297,
      "longitude": 128.325111
    },
    "name": "스키하우스",
    "resort": "휘닉스 파크",
    "timestamp": "2025-04-21T13:27:13.029168+09:00"
  },
  {
    "data": [
      {
        "humidity": 41.7,
        "rainfall": 0.0,
        "snow_cover": 0.0,
        "snowfall_3hr": 0.0,
        "temperature": 21.9,
        "time": "2025-04-21T12:25:00+09:00",
        "wind_speed": 1.1
      }
    ],
    "location": {
      "latitude": 37.573736,
      "longitude": 128.322129
    },
    "name": "불새마루",
    "resort": "휘닉스 파크",
    "timestamp": "2025-04-21T13:27:13.130361+09:00"
  },
  {
    "data": [
      {
        "humidity": 44.2,
        "rainfall": 0.0,
        "snow_cover": 0.0,
        "snowfall_3hr": 0.0,
        "temperature": 21.6,
        "time": "2025-04-21T12:25:00+09:00",
        "wind_speed": 1.1
      }
    ],
    "location": {
      "latitude": 37.57409,
      "longitude": 128.310128
    },
    "name": "몽블랑 정상",
    "resort": "휘닉스 파크",
    "timestamp": "2025-04-21T13:27:13.231678+09:00"
  },
  {
    "data": [
      {
        "humidity": 43.4,
        "rainfall": 0.0,
        "snow_cover": 0.0,
        "snowfall_3hr": 0.0,
        "temperature": 21.7,
        "time": "2025-04-21T12:25:00+09:00",
        "wind_speed": 1.1
      }
    ],
    "location": {
      "latitude": 37.581563,
      "longitude": 128.312577
    },
    "name": "스패로우 상단",
    "resort": "휘닉스 파크",
    "timestamp": "2025-04-21T13:27:13.332823+09:00"
  },
  {
    "data": [
      {
        "humidity": 48.6,
        "rainfall": 0.0,
        "snow_cover": 0.0,
        "snowfall_3hr": 0.0,
        "temperature": 19.5,
        "time": "2025-04-21T12:25:00+09:00",
        "wind_speed": 3.1
      }
    ],
    "location": {
      "latitude": 37.207905,
      "longitude": 128.825829
    },
    "name": "스키하우스",
    "resort": "하이원 리조트",
    "timestamp": "2025-04-21T13:27:14.922471+09:00"
  },
  {
    "data": [
      {
        "humidity": 46.7,
        "rainfall": 0.0,
        "snow_cover": 0.0,
        "snowfall_3hr": 0.0,
        "temperature": 17.3,
        "time": "2025-04-21T12:25:00+09:00",
        "wind_speed": 3.1
      }
    ],
    "location": {
      "latitude": 37.194318,
      "longitude": 128.81989
    },
    "name": "마운틴허브",
    "resort": "하이원 리조트",
    "timestamp": "2025-04-21T13:27:15.057611+09:00"
  },
  {
    "data": [
      {
        "humidity": 54.2,
        "rainfall": 0.0,
        "snow_cover": 0.0,
        "snowfall_3hr": 0.0,
        "temperature": 16.0,
        "time": "2025-04-21T12:25:00+09:00",
        "wind_speed": 3.0
      }
    ],
    "location": {
      "latitude": 37.183029,
      "longitude": 128.817148
    },
    "name": "마운틴탑",
    "resort": "하이원 리조트",
    "timestamp": "2025-04-21T13:27:15.086795+09:00"
  },
  {
    "data": [
      {
        "humidity": 44.5,
        "rainfall": 0.0,
        "snow_cover": 0.0,
        "snowfall_3hr": 0.0,
        "temperature": 20.4,
        "time": "2025-04-21T12:25:00+09:00",
        "wind_speed": 3.1
      }
    ],
    "location": {
      "latitude": 37.204624,
      "longitude": 128.839496
    },
    "name": "밸리 스키하우스",
    "resort": "하이원 리조트",
    "timestamp": "2025-04-21T13:27:15.127406+09:00"
  },
  {
    "data": [
      {
        "humidity": 47.4,
        "rainfall": 0.0,
        "snow_cover": 0.0,
        "snowfall_3hr": 0.0,
        "temperature": 17.0,
        "time": "2025-04-21T12:25:00+09:00",
        "wind_speed": 3.1
      }
    ],
    "location": {
      "latitude": 37.190277,
      "longitude": 128.827839
    },
    "name": "밸리허브",
    "resort": "하이원 리조트",
    "timestamp": "2025-04-21T13:27:15.146168+09:00"
  },
  {
    "data": [
      {
        "humidity": 61.8,
        "rainfall": 0.0,
        "snow_cover": 0.0,
        "snowfall_3hr": 0.0,
        "temperature": 14.9,
        "time": "2025-04-21T12:25:00+09:00",
        "wind_speed": 3.1
      }
    ],
    "location": {
      "latitude": 37.178382,
      "longitude": 128.830052
    },
    "name": "밸리탑",
    "resort": "하이원 리조트",
    "timestamp": "2025-04-21T13:27:15.246274+09:00"
  },
  {
    "data": [
      {
        "humidity": 80.5,
        "rainfall": 0.0,
        "snow_cover": 0.0,
        "snowfall_3hr": 0.0,
        "temperature": 17.6,
        "time": "2025-04-21T12:25:00+09:00",
        "wind_speed": 0.9
      }
    ],
    "location": {
      "latitude": 35.890715,
      "longitude": 127.736869
    },
    "name": "스키하우스",
    "resort": "무주 덕유산 리조트",
    "timestamp": "2025-04-21T13:27:15.947177+09:00"
  },
  {
    "data": [
      {
        "humidity": 77.1,
        "rainfall": 0.0,
        "snow_cover": 0.0,
        "snowfall_3hr": 0.0,
        "temperature": 17.9,
        "time": "2025-04-21T12:25:00+09:00",
        "wind_speed": 1.1
      }
    ],
    "location": {
      "latitude": 35.888912,
      "longitude": 127.744951
    },
    "name": "설천 베이스",
    "resort": "무주 덕유산 리조트",
    "timestamp": "2025-04-21T13:27:16.254318+09:00"
  },
  {
    "data": [
      {
        "humidity": 90.3,
        "rainfall": 0.0,
        "snow_cover": 0.0,
        "snowfall_3hr": 0.0,
        "temperature": 14.5,
        "time": "2025-04-21T12:25:00+09:00",
        "wind_speed": 1.0
      }
    ],
    "location": {
      "latitude": 35.875487,
      "longitude": 127.753471
    },
    "name": "돌체 휴게소",
    "resort": "무주 덕유산 리조트",
    "timestamp": "2025-04-21T13:27:16.576378+09:00"
  },
  {
    "data": [
      {
        "humidity": 78.3,
        "rainfall": 0.0,
        "snow_cover": 0.0,
        "snowfall_3hr": 0.0,
        "temperature": 16.2,
        "time": "2025-04-21T12:25:00+09:00",
        "wind_speed": 0.8
      }
    ],
    "location": {
      "latitude": 35.864571,
      "longitude": 127.744477
    },
    "name": "설천봉 정상",
    "resort": "무주 덕유산 리조트",
    "timestamp": "2025-04-21T13:27:16.580705+09:00"
  },
  {
    "data": [
      {
        "humidity": 78.0,
        "rainfall": 0.0,
        "snow_cover": 0.0,
        "snowfall_3hr": 0.0,
        "temperature": 16.3,
        "time": "2025-04-21T12:25:00+09:00",
        "wind_speed": 0.8
      }
    ],
    "location": {
      "latitude": 35.882124,
      "longitude": 127.730632
    },
    "name": "하이디 하우스",
    "resort": "무주 덕유산 리조트",
    "timestamp": "2025-04-21T13:27:16.688799+09:00"
  },
  {
    "data": [
      {
        "humidity": 85.7,
        "rainfall": 0.0,
        "snow_cover": 0.0,
        "snowfall_3hr": 0.0,
        "temperature": 15.1,
        "time": "2025-04-21T12:25:00+09:00",
        "wind_speed": 0.8
      }
    ],
    "location": {
      "latitude": 35.876809,
      "longitude": 127.735373
    },
    "name": "만선봉 정상",
    "resort": "무주 덕유산 리조트",
    "timestamp": "2025-04-21T13:27:16.801706+09:00"
  },
  {
    "data": [
      {
        "humidity": 78.0,
        "rainfall": 0.0,
        "snow_cover": 0.0,
        "snowfall_3hr": 0.0,
        "temperature": 16.3,
        "time": "2025-04-21T12:25:00+09:00",
        "wind_speed": 0.9
      }
    ],
    "location": {
      "latitude": 35.881938,
      "longitude": 127.744772
    },
    "name": "스피츠하단 상단",
    "resort": "무주 덕유산 리조트",
    "timestamp": "2025-04-21T13:27:16.810639+09:00"
  },
  {
    "data": [
      {
        "humidity": 50.3,
        "rainfall": 0.0,
        "snow_cover": 0.0,
        "snowfall_3hr": 0.0,
        "temperature": 22.6,
        "time": "2025-04-21T12:25:00+09:00",
        "wind_speed": 0.8
      }
    ],
    "location": {
      "latitude": 37.649252,
      "longitude": 127.257067
    },
    "name": "스키하우스",
    "resort": "서울리조트",
    "timestamp": "2025-04-21T13:27:10.397992+09:00"
  },
  {
    "data": [
      {
        "humidity": 47.5,
        "rainfall": 0.0,
        "snow_cover": 0.0,
        "snowfall_3hr": 0.0,
        "temperature": 23.9,
        "time": "2025-04-21T12:25:00+09:00",
        "wind_speed": 0.8
      }
    ],
    "location": {
      "latitude": 37.662544,
      "longitude": 127.270042
    },
    "name": "스키하우스",
    "resort": "스타힐 리조트",
    "timestamp": "2025-04-21T13:27:10.499101+09:00"
  },
  {
    "data": [
      {
        "humidity": 52.0,
        "rainfall": 0.0,
        "snow_cover": 0.0,
        "snowfall_3hr": 0.0,
        "temperature": 23.2,
        "time": "2025-04-21T12:25:00+09:00",
        "wind_speed": 1.2
      }
    ],
    "location": {
      "latitude": 37.211926,
      "longitude": 127.295119
    },
    "name": "스키하우스",
    "resort": "양지파인리조트",
    "timestamp": "2025-04-21T13:27:11.005134+09:00"
  },
  {
    "data": [
      {
        "humidity": 46.1,
        "rainfall": 0.0,
        "snow_cover": 0.0,
        "snowfall_3hr": 0.0,
        "temperature": 24.2,
        "time": "2025-04-21T12:25:00+09:00",
        "wind_speed": 0.9
      }
    ],
    "location": {
      "latitude": 37.796762,
      "longitude": 127.247262
    },
    "name": "스키하우스",
    "resort": "베어스타운 리조트",
    "timestamp": "2025-04-21T13:27:10.903967+09:00"
  },
  {
    "data": [
      {
        "humidity": 55.2,
        "rainfall": 0.0,
        "snow_cover": 0.0,
        "snowfall_3hr": 0.0,
        "temperature": 21.0,
        "time": "2025-04-21T12:25:00+09:00",
        "wind_speed": 4.2
      }
    ],
    "location": {
      "latitude": 36.849602,
      "longitude": 127.974005
    },
    "name": "스키하우스",
    "resort": "수안보 이글밸리 스키리조트",
    "timestamp": "2025-04-21T13:27:13.433967+09:00"
  },
  {
    "data": [
      {
        "humidity": 51.5,
        "rainfall": 0.0,
        "snow_cover": 0.0,
        "snowfall_3hr": 0.0,
        "temperature": 19.8,
        "time": "2025-04-21T12:25:00+09:00",
        "wind_speed": 1.8
      }
    ],
    "location": {
      "latitude": 38.264809,
      "longitude": 128.378727
    },
    "name": "스키하우스",
    "resort": "알프스리조트",
    "timestamp": "2025-04-21T13:27:15.926956+09:00"
  },
  {
    "data": [
      {
        "humidity": null,
        "rainfall": null,
        "snow_cover": null,
        "snowfall_3hr": null,
        "temperature": 23.7,
        "time": "2025-04-21T13:27:08.572620+09:00",
        "weather_condition": null,
        "wind_speed": null
      }
    ],
    "location": {
      "latitude": null,
      "longitude": null
    },
    "name": "리조트_베이스",
    "resort": "곤지암리조트",
    "timestamp": "2025-04-21T13:27:08.572620+09:00"
  },
  {
    "data": [
      {
        "humidity": 40.0,
        "rainfall": null,
        "snow_cover": null,
        "snowfall_3hr": null,
        "temperature": 20.7,
        "time": "2025-04-21T13:27:09.250380+09:00",
        "weather_condition": null,
        "wind_speed": 0.4
      }
    ],
    "location": {
      "latitude": null,
      "longitude": null
    },
    "name": "리조트_만선베이스",
    "resort": "무주 덕유산 리조트",
    "timestamp": "2025-04-21T13:27:09.250380+09:00"
  },
  {
    "data": [
      {
        "humidity": 58.0,
        "rainfall": null,
        "snow_cover": null,
        "snowfall_3hr": null,
        "temperature": 20.0,
        "time": "2025-04-21T13:27:09.250380+09:00",
        "weather_condition": null,
        "wind_speed": 2.5
      }
    ],
    "location": {
      "latitude": null,
      "longitude": null
    },
    "name": "리조트_설천베이스",
    "resort": "무주 덕유산 리조트",
    "timestamp": "2025-04-21T13:27:09.250380+09:00"
  },
  {
    "data": [
      {
        "humidity": 63.0,
        "rainfall": null,
        "snow_cover": null,
        "snowfall_3hr": null,
        "temperature": 17.6,
        "time": "2025-04-21T13:27:09.250380+09:00",
        "weather_condition": null,
        "wind_speed": 1.6
      }
    ],
    "location": {
      "latitude": null,
      "longitude": null
    },
    "name": "리조트_미드피크",
    "resort": "무주 덕유산 리조트",
    "timestamp": "2025-04-21T13:27:09.250380+09:00"
  },
  {
    "data": [
      {
        "humidity": 74.0,
        "rainfall": null,
        "snow_cover": null,
        "snowfall_3hr": null,
        "temperature": 17.8,
        "time": "2025-04-21T13:27:09.250380+09:00",
        "weather_condition": null,
        "wind_speed": 0.7
      }
    ],
    "location": {
      "latitude": null,
      "longitude": null
    },
    "name": "리조트_만선봉",
    "resort": "무주 덕유산 리조트",
    "timestamp": "2025-04-21T13:27:09.250380+09:00"
  },
  {
    "data": [
      {
        "humidity": 77.0,
        "rainfall": null,
        "snow_cover": null,
        "snowfall_3hr": null,
        "temperature": 13.0,
        "time": "2025-04-21T13:27:09.250380+09:00",
        "weather_condition": null,
        "wind_speed": 0.6
      }
    ],
    "location": {
      "latitude": null,
      "longitude": null
    },
    "name": "리조트_설천봉",
    "resort": "무주 덕유산 리조트",
    "timestamp": "2025-04-21T13:27:09.250380+09:00"
  }
]